dsb_spider/__init__.py
dsb_spider/checker.py
dsb_spider/req.py
dsb_spider/sched.py
dsb_spider/tasker.py
dsb_spider/timer.py
dsb_spider/utils.py
dsb_spider/log/__init__.py
dsb_spider/log/color_codes.py
dsb_spider/log/ex.py
dsb_spider/log/formatter.py
dsb_spider-0.2.17.dist-info/METADATA
dsb_spider-0.2.17.dist-info/WHEEL
dsb_spider-0.2.17.dist-info/top_level.txt
dsb_spider-0.2.17.dist-info/RECORD
